helloworld.py
helloworld_v3030-0.0.1.dist-info/METADATA
helloworld_v3030-0.0.1.dist-info/WHEEL
helloworld_v3030-0.0.1.dist-info/top_level.txt
helloworld_v3030-0.0.1.dist-info/RECORD
